jarm/__init__.py
jarm/__main__.py
jarm/cli.py
jarm/constants.py
jarm/alpns/__init__.py
jarm/alpns/alpns.py
jarm/ciphers/__init__.py
jarm/ciphers/ciphers.py
jarm/connection/__init__.py
jarm/connection/connection.py
jarm/exceptions/__init__.py
jarm/exceptions/exceptions.py
jarm/formats/__init__.py
jarm/formats/common.py
jarm/formats/tls_1_1_middle_out.py
jarm/formats/tls_1_2_bottom_half.py
jarm/formats/tls_1_2_forward.py
jarm/formats/tls_1_2_middle_out.py
jarm/formats/tls_1_2_reverse.py
jarm/formats/tls_1_2_top_half.py
jarm/formats/tls_1_3_forward.py
jarm/formats/tls_1_3_invalid.py
jarm/formats/tls_1_3_middle_out.py
jarm/formats/tls_1_3_reverse.py
jarm/grease/__init__.py
jarm/grease/grease.py
jarm/hashing/__init__.py
jarm/hashing/hashing.py
jarm/packet/__init__.py
jarm/packet/packet.py
jarm/proxy/__init__.py
jarm/proxy/proxy.py
jarm/scanner/__init__.py
jarm/scanner/scanner.py
jarm/validate/__init__.py
jarm/validate/validate.py
jarm/versions/__init__.py
jarm/versions/versions.py
tests/__init__.py
tests/test_record.py
pyjarm-0.0.5.dist-info/LICENSE
pyjarm-0.0.5.dist-info/METADATA
pyjarm-0.0.5.dist-info/WHEEL
pyjarm-0.0.5.dist-info/entry_points.txt
pyjarm-0.0.5.dist-info/top_level.txt
pyjarm-0.0.5.dist-info/RECORD
