Metadata-Version: 2.1
Name: pyjarm
Version: 0.0.5
Summary: pyJarm is a convenience library for the JARM fingerprinting tool.
Home-page: UNKNOWN
Author: Andrew Scott
License: ISC
Keywords: expanse,palo alto,jarm
Platform: UNKNOWN
Classifier: Development Status :: 2 - Pre-Alpha
Classifier: Intended Audience :: Developers
Classifier: Topic :: Software Development
Classifier: Topic :: Software Development :: Libraries
Classifier: Topic :: Software Development :: Libraries :: Application Frameworks
Classifier: Programming Language :: Python :: 3
Classifier: Programming Language :: Python :: 3.6
Classifier: Programming Language :: Python :: 3.7
Classifier: Programming Language :: Python :: 3.8
Requires-Python: >=3.7
